aerofoil/__init__.py
aerofoil/aerofoil_backfill.py
aerofoil/aerofoil_plugin.py
aerofoil/models/backfill.py
aerofoil/models/reset_dag.py
aerofoil/operators/bash.py
aerofoil/sensors/backfill_sensor.py
aerofoil/templates/aerofoil/backfill.html
aerofoil/templates/aerofoil/fake_success.html
aerofoil/templates/aerofoil/reset.html
aerofoil/templates/aerofoil/restart.html
aerofoil/templates/aerofoil/version.html
aerofoil/utils/web_utils.py
aerofoil/views/backfill_view.py
aerofoil/views/mydags_view.py
aerofoil/views/reset_view.py
aerofoil/views/restart_view.py
aerofoil/views/version_view.py
apache_airflow_providers_aerofoil2-1.0.0.dist-info/LICENSE.md
apache_airflow_providers_aerofoil2-1.0.0.dist-info/METADATA
apache_airflow_providers_aerofoil2-1.0.0.dist-info/WHEEL
apache_airflow_providers_aerofoil2-1.0.0.dist-info/entry_points.txt
apache_airflow_providers_aerofoil2-1.0.0.dist-info/top_level.txt
apache_airflow_providers_aerofoil2-1.0.0.dist-info/RECORD
